{"cases":[{"case_id":"cubic_gradjit_f32_s","fn":"cubic","in_avals":[{"dtype":"float32","rng":"rand_default","shape":[]}],"mode":"grad_jit"},{"case_id":"cubic_gradjit_f64_s","fn":"cubic","in_avals":[{"dtype":"float64","rng":"rand_default","shape":[]}],"mode":"grad_jit"},{"case_id":"cubic_jit_f32_3","fn":"cubic","in_avals":[{"dtype":"float32","rng":"rand_default","shape":[3]}],"mode":"jit"},{"case_id":"cubic_jit_f32_s","fn":"cubic","in_avals":[{"dtype":"float32","rng":"rand_default","shape":[]}],"mode":"jit"},{"case_id":"cubic_jvpjit_f32_3","fn":"cubic","in_avals":[{"dtype":"float32","rng":"rand_default","shape":[3]}],"mode":"jvp_jit"},{"case_id":"cubic_vmapjit_f32_5x3","fn":"cubic","in_avals":[{"dtype":"float32","rng":"rand_default","shape":[5,3]}],"in_axes":[0],"mode":"vmap_jit"},{"case_id":"exp_neg_jit_f32_3","fn":"exp_neg","in_avals":[{"dtype":"float32","rng":"rand_default","shape":[3]}],"mode":"jit"},{"case_id":"nested2_jit_f32_s","fn":"nested2","in_avals":[{"dtype":"float32","rng":"rand_default","shape":[]}],"mode":"nested2_jit"},{"case_id":"nested2_jit_f64_s","fn":"nested2","in_avals":[{"dtype":"float64","rng":"rand_default","shape":[]}],"mode":"nested2_jit"},{"case_id":"nested2_vmap_f32_3","fn":"nested2","in_avals":[{"dtype":"float32","rng":"rand_default","shape":[3]}],"in_axes":[0],"mode":"nested2_vmap"},{"case_id":"sin_jit_f32_3","fn":"sin","in_avals":[{"dtype":"float32","rng":"rand_default","shape":[3]}],"mode":"jit"},{"case_id":"sin_jit_f64_3","fn":"sin","in_avals":[{"dtype":"float64","rng":"rand_default","shape":[3]}],"mode":"jit"},{"case_id":"sin_jvpjit_f32_3","fn":"sin","in_avals":[{"dtype":"float32","rng":"rand_default","shape":[3]}],"mode":"jvp_jit"},{"case_id":"sin_jvpjit_f64_3","fn":"sin","in_avals":[{"dtype":"float64","rng":"rand_default","shape":[3]}],"mode":"jvp_jit"},{"case_id":"sin_mul_jit_f32_3","fn":"sin_mul","in_avals":[{"dtype":"float32","rng":"rand_default","shape":[3]},{"dtype":"float32","rng":"rand_default","shape":[3]}],"mode":"jit"},{"case_id":"sin_mul_jvpjit_f32_3","fn":"sin_mul","in_avals":[{"dtype":"float32","rng":"rand_default","shape":[3]},{"dtype":"float32","rng":"rand_default","shape":[3]}],"mode":"jvp_jit"},{"case_id":"sin_mul_vmapjit_f32_5x3","fn":"sin_mul","in_avals":[{"dtype":"float32","rng":"rand_default","shape":[5,3]},{"dtype":"float32","rng":"rand_default","shape":[5,3]}],"in_axes":[0,0],"mode":"vmap_jit"},{"case_id":"sin_vmapjit_f32_5x3","fn":"sin","in_avals":[{"dtype":"float32","rng":"rand_default","shape":[5,3]}],"in_axes":[0],"mode":"vmap_jit"},{"case_id":"sin_vmapjit_f64_5x3","fn":"sin","in_avals":[{"dtype":"float64","rng":"rand_default","shape":[5,3]}],"in_axes":[0],"mode":"vmap_jit"},{"case_id":"sum_sin_gradjit_f32_3","fn":"sum_sin","in_avals":[{"dtype":"float32","rng":"rand_default","shape":[3]}],"mode":"grad_jit"},{"case_id":"tanh_jit_f32_3","fn":"tanh","in_avals":[{"dtype":"float32","rng":"rand_default","shape":[3]}],"mode":"jit"}],"module":"api","num_generated_cases":10,"schema_version":1}
